pgtk/__init__.py
pgtk/pgtk.py
postgis_toolkit-0.0.1.dist-info/METADATA
postgis_toolkit-0.0.1.dist-info/WHEEL
postgis_toolkit-0.0.1.dist-info/entry_points.txt
postgis_toolkit-0.0.1.dist-info/top_level.txt
postgis_toolkit-0.0.1.dist-info/RECORD
