Metadata-Version: 2.1
Name: postgis-toolkit
Version: 0.0.1
Summary: PostGIS Commands
Home-page: https://github.com/felixink/postgis-toolkit
Author: Felix Rhett
Author-email: felix.rhett@gmail.com
License: MIT
Keywords: postgis,postgres,gis,shapefile,pgsql2shp
Platform: UNKNOWN
Classifier: License :: OSI Approved :: MIT License
Classifier: Programming Language :: Python :: 3
Classifier: Programming Language :: Python :: 3.7
Requires-Python: >=3.7*
Requires-Dist: Click
Requires-Dist: psycopg2-binary
Requires-Dist: tabulate
